libphysfs.so.1
libphysfs.so.3.3.0
libphysfs.so
physfs.cpython-39-i386-linux-gnu.so
physfs.py-0.2.0.dist-info/LICENSE
physfs.py-0.2.0.dist-info/METADATA
physfs.py-0.2.0.dist-info/RECORD
physfs.py-0.2.0.dist-info/top_level.txt
physfs.py-0.2.0.dist-info/WHEEL
