Metadata-Version: 2.1
Name: physfs.py
Version: 0.2.0
Summary: PhysFS.py is a python wrapper for the PhysicsFS library.
Home-page: https://github.com/shabbywu/physfs.py
Author: shabbywu
Author-email: shabbywu@qq.com
Requires-Python: >=3.7
License-File: LICENSE
Provides-Extra: test
Requires-Dist: pytest ; extra == 'test'
